{
    "meglepetést készítettem" : "Préparer une surise",
    "egy hétvége utazást ígértem" : "j'ai promis un voyage sur un weekend",
    "Két nappal indulàs előtt" : "Deux jours avant le départ",
    "meleg ruhat kell" : "Des vetements chauds sont nécessaire",
    "Mondtam azt is, hogy Mànyra mennünk" : "J'ai aussi dit qu'on allait à Many",
    "repülőjegyek olcsóbbak voltak" : "Les billets d'avions étaient cher",
    "Csak 40 perccel indulás előtt tudta meg, hogy Svédországba megyünk": "J'ai dit qu'on alait en suède juste 40 minutes avant le départ",
    "De nem panaszkodtunk" : "Nous ne nous sommes pas plaint",
    "Egy 200km/órás vonattal utaztunk" : "On a voyagé avec une train qui va a 200km/h",
    "jegyellenőr lány" : "une contoleuse",
    "naivak és őszinték" : "Naïfs et honnêtes",
    "nem tudom, hogy jò-e gasztronomìa Svédorszagban" : "Je ne sais pas comme la gasztronomie est bonne en suède",
    "de ràjöttem, hogy mindent jòl föznek" : "Mais j'ai réalisé à quel point ils cuisinent bien",
    "Ilyen felséges illat pékségben" : "Le odeurs sons tellement délicieuses dans la boulangerie",
    "Egy magyar muvesz kiallitasát is megnéztük" : "Nous avons regardé une expo d'une artiste hongroise",
    "Vasarnap, magyarorsagra jöttünk" : "On et revenu en hongrie dimanche",
    "a pilota (aki nem anyam) mondta" : "Le pilote (qui n'est pas ma mère) a dit:",
    "1934-es filmváltozatot" : "la version du film de 1934",
    "Ma mehetunk tovább MagyarOK könyben" : "Aujourd'hui on peut aller plus loins dans le livre MagyarOK"
}
